rath/__init__.py
rath/errors.py
rath/operation.py
rath/py.typed
rath/rath.py
rath/scalars.py
rath/traits.py
rath/links/__init__.py
rath/links/aiohttp.py
rath/links/auth.py
rath/links/base.py
rath/links/compose.py
rath/links/dictinglink.py
rath/links/errors.py
rath/links/file.py
rath/links/foward.py
rath/links/graphql_ws.py
rath/links/httpx.py
rath/links/log.py
rath/links/parsing.py
rath/links/retry.py
rath/links/shrink.py
rath/links/sign_local_link.py
rath/links/split.py
rath/links/subscription_transport_ws.py
rath/links/timeout.py
rath/links/types.py
rath/links/utils.py
rath/links/validate.py
rath/links/testing/__init__.py
rath/links/testing/assert_link.py
rath/links/testing/direct_succeeding_link.py
rath/links/testing/mock.py
rath/links/testing/never_succeeding_link.py
rath/links/testing/statefulmock.py
rath/links/testing/utils.py
rath/turms/__init__.py
rath/turms/fragment.py
rath/turms/funcs.py
rath/turms/utils.py
rath-3.7.0.dist-info/METADATA
rath-3.7.0.dist-info/WHEEL
rath-3.7.0.dist-info/licenses/LICENSE
rath-3.7.0.dist-info/RECORD
