Metadata-Version: 2.4
Name: rath
Version: 3.7.0
Summary: async transport-agnostic graphql client
Author-email: jhnnsrs <jhnnsrs@gmail.com>
License-File: LICENSE
Requires-Python: >=3.11
Requires-Dist: graphql-core<4,>=3.2.0
Requires-Dist: koil>=2.0.3
Requires-Dist: pydantic>2
Provides-Extra: aiohttp
Requires-Dist: aiohttp<4,>=3.8.2; extra == 'aiohttp'
Requires-Dist: certifi>2021; extra == 'aiohttp'
Provides-Extra: httpx
Requires-Dist: httpx<0.24,>=0.23.0; extra == 'httpx'
Provides-Extra: signing
Requires-Dist: cryptography<42,>=41.0.3; extra == 'signing'
Provides-Extra: websockets
Requires-Dist: websockets~=10.2; extra == 'websockets'
